gotn/__init__.py
gotn/cli.py
gotn-0.3.0.dist-info/licenses/LICENSE
gotn-0.3.0.dist-info/METADATA
gotn-0.3.0.dist-info/WHEEL
gotn-0.3.0.dist-info/entry_points.txt
gotn-0.3.0.dist-info/top_level.txt
gotn-0.3.0.dist-info/RECORD
