Metadata-Version: 2.4
Name: gotn
Version: 0.3.0
License-File: LICENSE
Requires-Dist: requests
Requires-Dist: argparse
Dynamic: description
Dynamic: description-content-type
Dynamic: license-file
Dynamic: requires-dist
